README.rst
setup.py
mkflask_module.egg-info/PKG-INFO
mkflask_module.egg-info/SOURCES.txt
mkflask_module.egg-info/dependency_links.txt
mkflask_module.egg-info/entry_points.txt
mkflask_module.egg-info/top_level.txt
pip_module/__init__.py
pip_module/__main__.py
pip_module/awesome_module.py