Metadata-Version: 1.0
Name: mkflask-module
Version: 0.1.1
Summary: Python module
Home-page: https://github.com/Spracto/awesome_pip_module
Author: Barclay Iversen AKA Spracto
Author-email: barclayiversen@gmail.com
License: UNKNOWN
Platform: UNKNOWN
